{
"type": "FeatureCollection",
"name": "ouvrages_surveillance",
"crs": { "type": "name", "properties": { "name": "urn:ogc:def:crs:OGC:1.3:CRS84" } },
"features": [
{ "type": "Feature", "properties": { "id": "4a37fc34-74f0-4e60-9055-75aee276831b", "type_ouvrage": null, "date_inspection": null, "profondeur": 0.0, "commentaire": null, "documents": null }, "geometry": { "type": "Point", "coordinates": [ 2.638749952503118, 48.52961471467934 ] } }
]
}
