{
"type": "FeatureCollection",
"name": "ouvrages_surveillance",
"crs": { "type": "name", "properties": { "name": "urn:ogc:def:crs:OGC:1.3:CRS84" } },
"features": [
{ "type": "Feature", "properties": { "id": "e60489cd-9da7-46a5-a3bf-034cc687dad9", "type_ouvrage": null, "date_inspection": null, "profondeur": null, "commentaire": null, "documents": null }, "geometry": { "type": "Point", "coordinates": [ 2.638749952503118, 48.52961471467934 ] } }
]
}
