{
"type": "FeatureCollection",
"name": "ouvrages_surveillance",
"crs": { "type": "name", "properties": { "name": "urn:ogc:def:crs:OGC:1.3:CRS84" } },
"features": [
{ "type": "Feature", "properties": { "id": "70679f6a-c193-45dd-b702-6dabc227fd05", "type_ouvrage": "Piézomètre", "date_inspection": "11/01/2024", "profondeur": 10.0, "commentaire": "Ile Ouest. Première étape mission ADEME: bilan environnement, historique, activités, recensement usages hors site", "documents": null }, "geometry": { "type": "Point", "coordinates": [ 2.362342057130431, 48.523378549567013 ] } },
{ "type": "Feature", "properties": { "id": "5541ec42-ccf6-4341-9c63-64642c1936c9", "type_ouvrage": "Piézair", "date_inspection": "02/01/2024", "profondeur": 1.5, "commentaire": null, "documents": null }, "geometry": { "type": "Point", "coordinates": [ 2.362498868216848, 48.523130371785868 ] } }
]
}
